easier_openai/Images.py
easier_openai/__init__.py
easier_openai/assistant.py
easier_openai/decorators.py
easier_openai/models.py
easier_openai-6.1.1.dist-info/licenses/LICENSE
easier_openai-6.1.1.dist-info/METADATA
easier_openai-6.1.1.dist-info/WHEEL
easier_openai-6.1.1.dist-info/top_level.txt
easier_openai-6.1.1.dist-info/RECORD
