Metadata-Version: 2.4
Name: easier-openai
Version: 6.1.1
Summary: Utilities for orchestrating OpenAI chat, tool calling, search, audio, and images from one helper package.
Author-email: Advik Mathur <pranit.advik@gmail.com>
License-Expression: Apache-2.0
Project-URL: Homepage, https://github.com/Adpros7/easier-gpt
Project-URL: Repository, https://github.com/Adpros7/easier-gpt
Project-URL: Documentation, https://github.com/Adpros7/easier-gpt
Project-URL: Issues, https://github.com/Adpros7/easier-gpt/issues
Keywords: openai,assistant,chat,responses,audio,images,vector,speech
Classifier: Development Status :: 5 - Production/Stable
Classifier: Intended Audience :: Developers
Classifier: Programming Language :: Python :: 3
Classifier: Programming Language :: Python :: 3.13
Classifier: Topic :: Software Development :: Libraries :: Python Modules
Requires-Python: ==3.13.*
License-File: LICENSE
Requires-Dist: openai
Requires-Dist: simpleaudio
Requires-Dist: openai-stt
Requires-Dist: typing-extensions
Requires-Dist: huggingface-hub
Requires-Dist: playsound3
Requires-Dist: pygithub
Requires-Dist: pyaudio
Requires-Dist: websocket-client
Requires-Dist: audioop-lts
Requires-Dist: sounddevice
Provides-Extra: speech-models
Requires-Dist: openai-whisper>=20250625; extra == "speech-models"
Dynamic: license-file
